README.rst
setup.py
clc_msa_utils/__init__.py
clc_msa_utils/kv_store.py
clc_msa_utils/log_manager.py
clc_msa_utils/queueing.py
clc_msa_utils/utils.py
clc_msa_utils.egg-info/PKG-INFO
clc_msa_utils.egg-info/SOURCES.txt
clc_msa_utils.egg-info/dependency_links.txt
clc_msa_utils.egg-info/requires.txt
clc_msa_utils.egg-info/top_level.txt