Metadata-Version: 1.1
Name: clc-msa-utils
Version: 0.10.8
Summary: CenturyLink Managed Services Anywhere Python Utilities
Home-page: https://github.com/CenturyLinkCloud/mos-pyutils
Author: CenturyLink Managed Services Team
Author-email: managedos@ctl.io
License: MIT
Keywords: CenturyLink ManagedServices Utilities
Platform: UNKNOWN
Classifier: Development Status :: 5 - Production/Stable
Classifier: Intended Audience :: Developers
Classifier: Programming Language :: Python :: 3
Classifier: Programming Language :: Python :: 3.3
Classifier: Programming Language :: Python :: 3.4
Classifier: Programming Language :: Python :: 3.5
Classifier: Programming Language :: Python :: 3.6
